Metadata-Version: 2.1
Name: data-quality-control
Version: 0.1.0
Summary: Python code to perform data quality control on wind energy data, especially meteorological data
Home-page: https://github.com/ashimgiyanani/data_quality_control
Download-URL: https://github.com/ashimgiyanani/data_quality_control/archive/refs/tags/v0.1.0.tar.gz
Author: Ashim Giyanani
Author-email: ashimgiyanani@yahoo.com
License: BSD License
Keywords: python,qualitycontrol,lidar,windenergy
Classifier: Development Status :: 3 - Alpha
Classifier: Intended Audience :: Developers
Classifier: Topic :: Scientific/Engineering :: Atmospheric Science
Classifier: License :: OSI Approved :: BSD License
Classifier: Programming Language :: Python :: 3
Classifier: Programming Language :: Python :: 3.9
Classifier: Programming Language :: Python :: 3.10
Requires-Python: >=3.9
License-File: LICENSE
